bagulho/__init__.py
bagulho/cli.py
bagulho-0.1.0.dist-info/entry_points.txt
bagulho-0.1.0.dist-info/WHEEL
bagulho-0.1.0.dist-info/METADATA
bagulho-0.1.0.dist-info/RECORD
