Metadata-Version: 2.1
Name: bagulho
Version: 0.1.0
Summary: 
Author: dunossauro
Author-email: mendesxeduardo@gmail.com
Requires-Python: >=3.9,<4.0
Classifier: Programming Language :: Python :: 3
Classifier: Programming Language :: Python :: 3.9
Requires-Dist: httpx (>=0.19.0,<0.20.0)
